MANIFEST.in
README.org
pyproject.toml
setup.cfg
setup.py
kingston/__init__.py
kingston/aop.py
kingston/bintools.py
kingston/build.py
kingston/decl.py
kingston/devtool.py
kingston/dig.py
kingston/fsm.py
kingston/kind.py
kingston/lang.py
kingston/lazy.py
kingston/match.py
kingston/microscope.py
kingston/py.typed
kingston/testing.py
kingston/view.py
kingston/xxx_kind.py
kingston.egg-info/PKG-INFO
kingston.egg-info/SOURCES.txt
kingston.egg-info/dependency_links.txt
kingston.egg-info/requires.txt
kingston.egg-info/top_level.txt