Metadata-Version: 2.1
Name: kingston
Version: 0.7.8
Summary: Some Python nicieties
Home-page: https://github.com/jacob414/kingston
Author: Jacob Oscarson
Author-email: jacob@414soft.com
License: MIT
Platform: UNKNOWN
Classifier: Programming Language :: Python
Classifier: Programming Language :: Python :: 2.7
Classifier: Programming Language :: Python :: 3
Classifier: Development Status :: 4 - Beta
Classifier: Intended Audience :: Developers
Classifier: License :: OSI Approved :: MIT License
Classifier: Operating System :: OS Independent
Provides-Extra: test
